LICENSE
README.md
lyyformula.py
setup.py
lyyformula.egg-info/PKG-INFO
lyyformula.egg-info/SOURCES.txt
lyyformula.egg-info/dependency_links.txt
lyyformula.egg-info/top_level.txt