Metadata-Version: 2.1
Name: lyyformula
Version: 1.3
Summary: lyyformula for lyy
Author: lyy
Author-email: 
License: MIT
License-File: LICENSE
